{
  "id": 4452,
  "type": 4171,
  "g": 4101,
  "project": 3891,
  "ads": 2180,
  "google": 2149,
  "keyword": 2047,
  "parent": 1909,
  "ad": 1838,
  "search": 1823,
  "resolvers": 1807,
  "context": 1715,
  "document": 1679,
  "service": 1670,
  "element": 1624,
  "shop": 1469,
  "name": 1427,
  "resolver": 1411,
  "get": 1410,
  "obj": 1370,
  "types": 1293,
  "data": 1141,
  "user": 1132,
  "entity": 1038,
  "maybe": 990,
  "analysis": 966,
  "scalars": 953,
  "options": 948,
  "performance": 944,
  "from": 929,
  "module": 923,
  "product": 909,
  "gaa": 907,
  "object": 891,
  "to": 837,
  "update": 836,
  "args": 831,
  "keywords": 821,
  "url": 796,
  "term": 756,
  "group": 754,
  "with": 749,
  "status": 739,
  "page": 703,
  "metrics": 701,
  "map": 690,
  "initialize": 690,
  "for": 683,
  "resource": 683,
  "construct": 681,
  "category": 676,
  "of": 672,
  "recommendation": 655,
  "array": 646,
  "conversion": 635,
  "len": 635,
  "job": 634,
  "repository": 627,
  "by": 618,
  "row": 616,
  "result": 607,
  "campaign": 590,
  "t": 589,
  "api": 576,
  "filter": 561,
  "match": 560,
  "is": 557,
  "terms": 536,
  "find": 535,
  "report": 523,
  "collection": 521,
  "logger": 516,
  "feed": 513,
  "query": 511,
  "info": 499,
  "settings": 471,
  "task": 468,
  "code": 458,
  "config": 455,
  "promise": 445,
  "all": 443,
  "date": 442,
  "rows": 440,
  "nullable": 435,
  "buffer": 435,
  "add": 412,
  "rate": 408,
  "email": 405,
  "input": 403,
  "database": 401,
  "provider": 399,
  "country": 392,
  "mutation": 391,
  "set": 388,
  "currency": 378,
  "score": 377,
  "error": 364,
  "readonly": 362,
  "brand": 359,
  "at": 352,
  "account": 352,
  "nest": 351,
  "words": 346,
  "source": 335,
  "conversions": 333,
  "price": 326,
  "item": 326,
  "projects": 322,
  "create": 322,
  "target": 320,
  "bidding": 311,
  "max": 299,
  "schema": 299,
  "cursor": 293,
  "response": 289,
  "strategy": 289,
  "min": 285,
  "one": 284,
  "injectable": 282,
  "db": 281,
  "blacklist": 281,
  "admin": 278,
  "opts": 278,
  "column": 271,
  "default": 270,
  "monitoring": 270,
  "delete": 268,
  "http": 266,
  "value": 261,
  "count": 259,
  "agenda": 258,
  "mongo": 254,
  "boom": 249,
  "non": 247,
  "equals": 244,
  "fields": 244,
  "substring": 240,
  "string": 239,
  "global": 239,
  "analytics": 238,
  "generator": 234,
  "length": 229,
  "last": 228,
  "interval": 225,
  "event": 225,
  "paused": 224,
  "ensure": 224,
  "mocked": 224,
  "enums": 223,
  "organic": 220,
  "ids": 220,
  "volume": 217,
  "expect": 216,
  "props": 216,
  "raw": 215,
  "link": 215,
  "recommendations": 214,
  "order": 213,
  "story": 212,
  "text": 208,
  "doc": 206,
  "graph": 206,
  "in": 205,
  "diff": 205,
  "be": 203,
  "property": 203,
  "call": 202,
  "deal": 202,
  "auth": 200,
  "bounce": 199,
  "base": 196,
  "ql": 196,
  "elements": 195,
  "position": 194,
  "customer": 194,
  "modern": 192,
  "sea": 191,
  "entities": 190,
  "fn": 190,
  "cost": 190,
  "progress": 187,
  "i": 185,
  "client": 185,
  "a": 184,
  "number": 183,
  "field": 183,
  "roas": 183,
  "limit": 180,
  "budget": 177,
  "domain": 176,
  "enabled": 176,
  "new": 174,
  "throw": 171,
  "results": 171,
  "visibility": 170,
  "accessible": 169,
  "any": 168,
  "start": 167,
  "console": 166,
  "existing": 166,
  "bad": 164,
  "push": 160,
  "key": 160,
  "action": 160,
  "index": 159,
  "not": 158,
  "clicks": 158,
  "serp": 157,
  "urls": 156,
  "make": 156,
  "created": 155,
  "require": 153,
  "remove": 152,
  "b": 151,
  "refresh": 151,
  "history": 151,
  "products": 150,
  "quality": 150,
  "c": 149,
  "cpc": 148,
  "deleted": 148,
  "resolve": 147,
  "e": 146,
  "r": 145,
  "path": 145,
  "parameters": 143,
  "tag": 143,
  "should": 142,
  "wrapper": 141,
  "typename": 140,
  "cache": 139,
  "system": 139,
  "activity": 139,
  "average": 136,
  "added": 136,
  "suggestion": 136,
  "parse": 134,
  "token": 134,
  "criterion": 134,
  "session": 134,
  "details": 133,
  "log": 131,
  "active": 130,
  "sort": 128,
  "check": 128,
  "organization": 128,
  "obsolete": 127,
  "request": 127,
  "website": 127,
  "monitor": 125,
  "upsert": 123,
  "boomerank": 123,
  "title": 122,
  "dayjs": 122,
  "scheduled": 122,
  "tracked": 120,
  "total": 119,
  "unique": 119,
  "on": 118,
  "random": 117,
  "message": 115,
  "too": 114,
  "person": 114,
  "language": 113,
  "first": 113,
  "pages": 111,
  "users": 111,
  "cached": 110,
  "migration": 110,
  "pipedrive": 110,
  "amount": 109,
  "management": 109,
  "has": 108,
  "partial": 108,
  "including": 108,
  "association": 108,
  "generate": 107,
  "server": 106,
  "performing": 105,
  "negative": 105,
  "it": 104,
  "moz": 104,
  "combination": 104,
  "list": 103,
  "manager": 103,
  "fetch": 102,
  "op": 102,
  "abstract": 102,
  "content": 101,
  "onboarding": 101,
  "stats": 100,
  "end": 100,
  "locale": 99,
  "per": 99,
  "impressions": 98,
  "location": 98,
  "and": 97,
  "favorite": 95,
  "pipeline": 95,
  "updated": 94,
  "template": 94,
  "mode": 94,
  "o": 93,
  "metric": 93,
  "identity": 93,
  "sum": 92,
  "node": 92,
  "time": 92,
  "merge": 92,
  "view": 92,
  "json": 91,
  "disabled": 91,
  "insert": 90,
  "removed": 90,
  "resources": 90,
  "description": 89,
  "previous": 88,
  "items": 88,
  "resolved": 88,
  "s": 87,
  "queue": 87,
  "enum": 87,
  "pick": 86,
  "initiator": 86,
  "k": 86,
  "low": 86,
  "categories": 84,
  "docs": 83,
  "prev": 83,
  "m": 82,
  "statistics": 82,
  "groups": 81,
  "batch": 81,
  "use": 81,
  "feeds": 81,
  "competitor": 80,
  "seo": 80,
  "includes": 80,
  "entry": 80,
  "tracking": 80,
  "usage": 80,
  "tracker": 80,
  "sessions": 80,
  "competition": 79,
  "run": 79,
  "suggestions": 78,
  "creation": 78,
  "missing": 77,
  "iterable": 76,
  "relevance": 76,
  "up": 76,
  "click": 76,
  "high": 76,
  "events": 75,
  "skip": 75,
  "required": 75,
  "top": 74,
  "access": 74,
  "alternatives": 74,
  "primary": 74,
  "bid": 74,
  "mock": 73,
  "jobs": 73,
  "notification": 73,
  "historical": 72,
  "documents": 72,
  "external": 72,
  "apply": 72,
  "theme": 72,
  "next": 71,
  "only": 71,
  "share": 71,
  "or": 70,
  "combine": 70,
  "goal": 70,
  "shopify": 70,
  "instance": 69,
  "timeout": 69,
  "daily": 69,
  "availability": 69,
  "deals": 69,
  "n": 68,
  "image": 68,
  "migrations": 68,
  "word": 67,
  "pending": 66,
  "stringify": 66,
  "private": 66,
  "mutex": 66,
  "bulk": 66,
  "basket": 66,
  "xml": 66,
  "duplicate": 65,
  "p": 65,
  "accounts": 65,
  "ecommerce": 64,
  "html": 64,
  "file": 64,
  "ref": 64,
  "role": 64,
  "attribution": 63,
  "x": 62,
  "size": 62,
  "replace": 61,
  "react": 61,
  "policy": 61,
  "mailchimp": 61,
  "margin": 61,
  "values": 60,
  "math": 60,
  "num": 60,
  "links": 60,
  "dispatcher": 60,
  "queries": 60,
  "model": 60,
  "impression": 60,
  "competitors": 59,
  "omit": 59,
  "many": 59,
  "init": 59,
  "brands": 59,
  "lock": 59,
  "timeframe": 59,
  "industry": 59,
  "preview": 58,
  "extensions": 57,
  "params": 57,
  "process": 57,
  "summary": 57,
  "micros": 57,
  "ranking": 56,
  "parsed": 56,
  "efficiency": 56,
  "current": 56,
  "sanitize": 56,
  "targeting": 56,
  "generation": 56,
  "stream": 56,
  "dcm": 56,
  "app": 55,
  "unknown": 55,
  "col": 55,
  "avg": 54,
  "ready": 54,
  "exact": 54,
  "calculate": 53,
  "generated": 53,
  "local": 53,
  "effect": 53,
  "delta": 53,
  "test": 52,
  "label": 52,
  "sync": 52,
  "full": 52,
  "geo": 52,
  "topic": 52,
  "inherited": 52,
  "priority": 52,
  "mail": 52,
  "slice": 51,
  "big": 51,
  "setup": 51,
  "changes": 51,
  "lead": 51,
  "codes": 51,
  "profit": 51,
  "expected": 50,
  "iterate": 50,
  "now": 50,
  "micro": 50,
  "null": 49,
  "age": 49,
  "automated": 49,
  "ctx": 49,
  "sites": 49,
  "slack": 49,
  "attributes": 49,
  "follower": 49,
  "boolean": 48,
  "related": 48,
  "root": 48,
  "profile": 48,
  "tech": 47,
  "before": 47,
  "int": 47,
  "execute": 47,
  "runner": 47,
  "weighted": 46,
  "blacklisted": 46,
  "calls": 46,
  "cpa": 46,
  "kw": 46,
  "meta": 46,
  "font": 46,
  "version": 45,
  "actions": 45,
  "executor": 45,
  "idea": 45,
  "str": 45,
  "difficulty": 44,
  "stat": 44,
  "hash": 44,
  "deprecated": 44,
  "scores": 44,
  "optional": 44,
  "change": 44,
  "stay": 44,
  "domains": 43,
  "equal": 43,
  "saved": 43,
  "blacklists": 43,
  "filters": 43,
  "after": 43,
  "simple": 43,
  "dependencies": 43,
  "compare": 42,
  "define": 42,
  "read": 42,
  "czech": 42,
  "px": 42,
  "h": 42,
  "load": 41,
  "nr": 41,
  "dispatch": 41,
  "perform": 41,
  "imports": 41,
  "helpers": 41,
  "styled": 41,
  "ratings": 40,
  "as": 40,
  "case": 40,
  "ne": 40,
  "st": 40,
  "converter": 40,
  "async": 40,
  "locked": 40,
  "verified": 40,
  "advertised": 40,
  "extension": 40,
  "subscription": 40,
  "have": 40,
  "been": 40,
  "seed": 40,
  "lower": 39,
  "password": 39,
  "err": 39,
  "direction": 39,
  "member": 39,
  "providers": 39,
  "typed": 38,
  "keys": 38,
  "multi": 38,
  "table": 38,
  "reason": 38,
  "exports": 38,
  "called": 38,
  "operations": 38,
  "additional": 38,
  "note": 38,
  "children": 37,
  "entries": 37,
  "invalid": 37,
  "campaigns": 37,
  "operation": 37,
  "blog": 37,
  "article": 37,
  "disable": 37,
  "pause": 37,
  "register": 37,
  "line": 37,
  "prop": 37,
  "sql": 37,
  "shopping": 36,
  "strength": 36,
  "flag": 36,
  "block": 36,
  "liked": 36,
  "prefix": 36,
  "buying": 35,
  "mobile": 35,
  "sub": 35,
  "callout": 35,
  "sitelink": 35,
  "pool": 35,
  "tips": 35,
  "generic": 35,
  "child": 34,
  "placement": 34,
  "weight": 34,
  "normalize": 34,
  "days": 34,
  "body": 34,
  "site": 34,
  "permission": 34,
  "valid": 34,
  "open": 34,
  "secondary": 34,
  "flat": 33,
  "credentials": 33,
  "maximize": 33,
  "focus": 33,
  "d": 32,
  "video": 32,
  "intent": 32,
  "potential": 32,
  "handle": 32,
  "v": 32,
  "login": 32,
  "handler": 32,
  "headline": 32,
  "projection": 32,
  "alternative": 32,
  "metabase": 32,
  "rmf": 32,
  "connection": 32,
  "operator": 31,
  "do": 31,
  "grouped": 31,
  "supported": 31,
  "constraint": 31,
  "auto": 31,
  "revenue": 31,
  "dbm": 31,
  "stage": 31,
  "q": 30,
  "jest": 30,
  "requests": 30,
  "agent": 30,
  "callback": 30,
  "minutes": 30,
  "spend": 30,
  "section": 30,
  "step": 30,
  "forward": 30,
  "criteria": 30,
  "insertable": 30,
  "spacing": 30,
  "complex": 30,
  "palatalise": 30,
  "impact": 29,
  "snippet": 29,
  "track": 29,
  "stories": 29,
  "definition": 29,
  "then": 29,
  "scheme": 29,
  "spending": 29,
  "xlsx": 29,
  "unreachable": 29,
  "factor": 29,
  "color": 29,
  "post": 29,
  "mapping": 28,
  "verification": 28,
  "scalar": 28,
  "iterator": 28,
  "manually": 28,
  "purchase": 28,
  "errors": 28,
  "matcher": 28,
  "fast": 28,
  "describe": 27,
  "no": 27,
  "width": 27,
  "unspecified": 27,
  "lowest": 27,
  "appearance": 27,
  "counting": 27,
  "inheritance": 27,
  "gte": 27,
  "positions": 26,
  "filtered": 26,
  "display": 26,
  "ms": 26,
  "vertical": 26,
  "upload": 26,
  "strict": 26,
  "month": 26,
  "fraction": 26,
  "tasks": 26,
  "configured": 26,
  "mapper": 26,
  "tree": 25,
  "subtract": 25,
  "format": 25,
  "hours": 25,
  "env": 25,
  "managed": 25,
  "migrate": 25,
  "control": 25,
  "duration": 25,
  "costs": 25,
  "done": 25,
  "ignored": 25,
  "can": 25,
  "replacement": 25,
  "tricks": 25,
  "height": 25,
  "constant": 25,
  "suggested": 25,
  "intermediate": 25,
  "thread": 25,
  "savings": 24,
  "old": 24,
  "secret": 24,
  "res": 24,
  "cleanup": 24,
  "legacy": 24,
  "strategies": 24,
  "z": 24,
  "replaced": 24,
  "setting": 24,
  "constraints": 24,
  "shared": 24,
  "updates": 24,
  "transaction": 24,
  "orm": 24,
  "relationship": 24,
  "persons": 24,
  "pattern": 23,
  "names": 23,
  "style": 23,
  "unordered": 23,
  "spent": 23,
  "started": 23,
  "join": 23,
  "services": 23,
  "each": 23,
  "slices": 23,
  "adwords": 23,
  "team": 23,
  "sources": 22,
  "desired": 22,
  "assert": 22,
  "parsing": 22,
  "original": 22,
  "send": 22,
  "failed": 22,
  "absolute": 22,
  "family": 22,
  "hostname": 22,
  "acc": 22,
  "lt": 22,
  "functionality": 22,
  "ds": 22,
  "stages": 22,
  "record": 21,
  "eur": 21,
  "single": 21,
  "occurrences": 21,
  "completed": 21,
  "factory": 21,
  "channel": 21,
  "responsive": 21,
  "koa": 21,
  "stopwords": 21,
  "languages": 21,
  "work": 21,
  "day": 21,
  "option": 21,
  "mailgun": 21,
  "padding": 21,
  "xx": 21,
  "lookup": 21,
  "native": 21,
  "activities": 21,
  "weights": 20,
  "extract": 20,
  "queued": 20,
  "href": 20,
  "schedule": 20,
  "ongoing": 20,
  "override": 20,
  "ended": 20,
  "paths": 20,
  "phone": 20,
  "picture": 20,
  "ui": 20,
  "inject": 20,
  "tester": 20,
  "sent": 20,
  "fonts": 20,
  "common": 20,
  "cohort": 20,
  "alltime": 20,
  "sets": 20,
  "arr": 19,
  "subdomain": 19,
  "dynamic": 19,
  "templates": 19,
  "runtime": 19,
  "grouping": 19,
  "descriptions": 19,
  "percent": 19,
  "separator": 19,
  "smart": 19,
  "restore": 19,
  "seen": 19,
  "verify": 19,
  "clean": 19,
  "changed": 19,
  "mongoose": 19,
  "reporting": 19,
  "matches": 19,
  "l": 19,
  "registry": 19,
  "split": 18,
  "allowed": 18,
  "concurrent": 18,
  "exclude": 18,
  "empty": 18,
  "application": 18,
  "batched": 18,
  "clear": 18,
  "trace": 18,
  "none": 18,
  "manual": 18,
  "ops": 18,
  "removal": 18,
  "regenerate": 18,
  "budgets": 18,
  "webhook": 18,
  "sheet": 18,
  "rel": 18,
  "src": 18,
  "td": 18,
  "tip": 18,
  "defined": 18,
  "mirror": 18,
  "comment": 18,
  "messages": 18,
  "sb": 18,
  "nodes": 17,
  "u": 17,
  "found": 17,
  "diffs": 17,
  "https": 17,
  "used": 17,
  "locations": 17,
  "stock": 17,
  "serialize": 17,
  "sentry": 17,
  "relation": 17,
  "reports": 17,
  "mutexes": 17,
  "cb": 17,
  "manage": 17,
  "tokens": 17,
  "plan": 17,
  "dashboard": 17,
  "freshchat": 17,
  "changelog": 17,
  "visible": 17,
  "trend": 17,
  "inspect": 17,
  "graphql": 17,
  "referrer": 17,
  "container": 17,
  "align": 17,
  "internal": 17,
  "regex": 17,
  "cannot": 17,
  "followers": 17,
  "assignment": 17,
  "recents": 17,
  "defaultable": 16,
  "pagination": 16,
  "val": 16,
  "reduce": 16,
  "did": 16,
  "strings": 16,
  "spill": 16,
  "indices": 16,
  "certificate": 16,
  "countries": 16,
  "headlines": 16,
  "checkout": 16,
  "cent": 16,
  "favorites": 16,
  "combinations": 16,
  "utc": 16,
  "collections": 16,
  "arrays": 16,
  "picks": 16,
  "cycle": 16,
  "social": 16,
  "layout": 16,
  "files": 16,
  "trim": 15,
  "multiple": 15,
  "uncached": 15,
  "linking": 15,
  "aws": 15,
  "environment": 15,
  "network": 15,
  "cpm": 15,
  "broad": 15,
  "ctr": 15,
  "columns": 15,
  "allow": 15,
  "main": 15,
  "warn": 15,
  "nth": 15,
  "mark": 15,
  "untyped": 15,
  "idx": 15,
  "normalized": 15,
  "rendering": 15,
  "cell": 15,
  "palette": 15,
  "sessionless": 15,
  "patterns": 15,
  "organizations": 15,
  "prices": 14,
  "cat": 14,
  "concat": 14,
  "dimension": 14,
  "level": 14,
  "expanded": 14,
  "address": 14,
  "mapped": 14,
  "bootstrap": 14,
  "write": 14,
  "final": 14,
  "improvement": 14,
  "destination": 14,
  "supports": 14,
  "unpause": 14,
  "success": 14,
  "goals": 14,
  "overlapping": 14,
  "commerce": 14,
  "automatic": 14,
  "lifetime": 14,
  "views": 14,
  "timestamp": 14,
  "heading": 14,
  "creative": 14,
  "objects": 14,
  "round": 13,
  "hints": 13,
  "selected": 13,
  "unused": 13,
  "checker": 13,
  "de": 13,
  "assign": 13,
  "device": 13,
  "char": 13,
  "profiler": 13,
  "historic": 13,
  "crawled": 13,
  "print": 13,
  "headers": 13,
  "out": 13,
  "money": 13,
  "mismatch": 13,
  "ceiling": 13,
  "float": 13,
  "subscribe": 13,
  "resolves": 13,
  "filename": 13,
  "uploaded": 13,
  "targets": 13,
  "boost": 13,
  "landing": 13,
  "audience": 13,
  "controllers": 13,
  "spy": 13,
  "bucket": 13,
  "put": 13,
  "host": 13,
  "timer": 13,
  "wait": 13,
  "state": 13,
  "subject": 13,
  "medium": 13,
  "defaults": 13,
  "singleton": 13,
  "recommend": 13,
  "router": 13,
  "param": 13,
  "wow": 13,
  "contains": 12,
  "rates": 12,
  "dev": 12,
  "concurrency": 12,
  "hashed": 12,
  "asset": 12,
  "excluded": 12,
  "header": 12,
  "w": 12,
  "ast": 12,
  "available": 12,
  "visit": 12,
  "solution": 12,
  "registration": 12,
  "ua": 12,
  "edit": 12,
  "linked": 12,
  "enable": 12,
  "refreshed": 12,
  "profitability": 12,
  "running": 12,
  "times": 12,
  "depth": 12,
  "hour": 12,
  "left": 12,
  "close": 12,
  "class": 12,
  "render": 12,
  "delivery": 12,
  "sending": 12,
  "background": 12,
  "filled": 12,
  "loader": 12,
  "dfp": 12,
  "migrator": 12,
  "owner": 12,
  "sdr": 12,
  "detection": 12,
  "best": 12,
  "helper": 12,
  "participant": 12,
  "roles": 12,
  "org": 11,
  "en": 11,
  "rest": 11,
  "phrase": 11,
  "other": 11,
  "an": 11,
  "plaintext": 11,
  "connections": 11,
  "ideas": 11,
  "advertising": 11,
  "scope": 11,
  "projected": 11,
  "demo": 11,
  "complete": 11,
  "fetched": 11,
  "levenshtein": 11,
  "evidence": 11,
  "implemented": 11,
  "customized": 11,
  "form": 11,
  "long": 11,
  "inactive": 11,
  "based": 11,
  "portfolio": 11,
  "duplicates": 11,
  "visibilities": 11,
  "hide": 11,
  "persist": 11,
  "monthly": 11,
  "recently": 11,
  "mocks": 11,
  "debug": 11,
  "parts": 11,
  "recommended": 11,
  "span": 11,
  "builder": 11,
  "segments": 11,
  "testers": 11,
  "re": 11,
  "evaluate": 11,
  "advertiser": 11,
  "journey": 11,
  "mikro": 11,
  "calculated": 11,
  "replacements": 11,
  "flow": 11,
  "recurring": 11,
  "does": 10,
  "contain": 10,
  "are": 10,
  "was": 10,
  "function": 10,
  "exchange": 10,
  "reject": 10,
  "place": 10,
  "authority": 10,
  "dimensions": 10,
  "inline": 10,
  "fix": 10,
  "head": 10,
  "part": 10,
  "comparisons": 10,
  "fs": 10,
  "stem": 10,
  "stopword": 10,
  "placeholder": 10,
  "growth": 10,
  "different": 10,
  "oauth": 10,
  "hidden": 10,
  "every": 10,
  "never": 10,
  "me": 10,
  "workers": 10,
  "caching": 10,
  "biddings": 10,
  "benchmark": 10,
  "without": 10,
  "readable": 10,
  "method": 10,
  "est": 10,
  "shopstory": 10,
  "markup": 10,
  "img": 10,
  "matchers": 10,
  "properties": 10,
  "marketing": 10,
  "pageviews": 10,
  "variant": 10,
  "adsense": 10,
  "publisher": 10,
  "adx": 10,
  "backfill": 10,
  "shopsystem": 10,
  "vocabulary": 10,
  "save": 10,
  "character": 10,
  "movements": 10,
  "assignments": 10,
  "dollar": 10,
  "than": 9,
  "questions": 9,
  "knowledge": 9,
  "mute": 9,
  "the": 9,
  "chars": 9,
  "na": 9,
  "expires": 9,
  "component": 9,
  "script": 9,
  "merged": 9,
  "connect": 9,
  "positive": 9,
  "promoted": 9,
  "kind": 9,
  "copy": 9,
  "invalidated": 9,
  "quote": 9,
  "occurrence": 9,
  "relative": 9,
  "through": 9,
  "fingerprint": 9,
  "disconnect": 9,
  "finish": 9,
  "automatically": 9,
  "revert": 9,
  "impl": 9,
  "matching": 9,
  "dom": 9,
  "gtm": 9,
  "gt": 9,
  "delay": 9,
  "reverted": 9,
  "eternal": 9,
  "intro": 9,
  "gclid": 9,
  "finding": 9,
  "exit": 9,
  "permissions": 9,
  "distribution": 9,
  "floodlight": 9,
  "js": 9,
  "synced": 9,
  "stack": 9,
  "csv": 9,
  "overlaps": 9,
  "outcome": 9,
  "payments": 9,
  "encbuf": 9,
  "hello": 9,
  "try": 8,
  "fallback": 8,
  "back": 8,
  "include": 8,
  "preferred": 8,
  "retry": 8,
  "latitude": 8,
  "longitude": 8,
  "profiles": 8,
  "pure": 8,
  "inner": 8,
  "webpage": 8,
  "custom": 8,
  "redirect": 8,
  "mappings": 8,
  "exists": 8,
  "snowball": 8,
  "when": 8,
  "floor": 8,
  "vanity": 8,
  "prescription": 8,
  "accept": 8,
  "contact": 8,
  "download": 8,
  "unresolved": 8,
  "ga": 8,
  "reconstruct": 8,
  "plugin": 8,
  "solutions": 8,
  "three": 8,
  "analysing": 8,
  "progresses": 8,
  "attrs": 8,
  "collect": 8,
  "counts": 8,
  "startup": 8,
  "command": 8,
  "aggregate": 8,
  "offset": 8,
  "attribute": 8,
  "since": 8,
  "horizontal": 8,
  "grpc": 8,
  "ssl": 8,
  "quantity": 8,
  "week": 8,
  "candidates": 8,
  "inactivity": 8,
  "busy": 8,
  "remote": 8,
  "chunks": 8,
  "rankings": 7,
  "rank": 7,
  "illegal": 7,
  "ceil": 7,
  "escape": 7,
  "during": 7,
  "distance": 7,
  "uri": 7,
  "region": 7,
  "range": 7,
  "metadata": 7,
  "spelling": 7,
  "more": 7,
  "starts": 7,
  "could": 7,
  "digest": 7,
  "socket": 7,
  "port": 7,
  "overrides": 7,
  "outrank": 7,
  "pharma": 7,
  "es": 7,
  "declined": 7,
  "decline": 7,
  "classic": 7,
  "cart": 7,
  "book": 7,
  "appointment": 7,
  "directions": 7,
  "qualified": 7,
  "signup": 7,
  "submit": 7,
  "paid": 7,
  "categorybrands": 7,
  "self": 7,
  "scopes": 7,
  "logout": 7,
  "advanced": 7,
  "steps": 7,
  "connected": 7,
  "placeholders": 7,
  "worker": 7,
  "if": 7,
  "skipping": 7,
  "alert": 7,
  "pgp": 7,
  "return": 7,
  "show": 7,
  "detail": 7,
  "border": 7,
  "paragraph": 7,
  "limits": 7,
  "dataloader": 7,
  "ordering": 7,
  "statuses": 7,
  "constants": 7,
  "visits": 7,
  "screen": 7,
  "promotion": 7,
  "repo": 7,
  "rotten": 7,
  "ftp": 7,
  "generators": 7,
  "capture": 7,
  "authorize": 7,
  "stringified": 7,
  "tokenize": 7,
  "slow": 7,
  "attachment": 7,
  "basic": 7,
  "installment": 7,
  "teams": 7,
  "webhooks": 7,
  "aggregation": 7,
  "deps": 7,
  "callbacks": 7,
  "chunk": 7,
  "rich": 6,
  "gi": 6,
  "second": 6,
  "fixed": 6,
  "under": 6,
  "equity": 6,
  "subdomains": 6,
  "linksto": 6,
  "lighthouse": 6,
  "searchconsole": 6,
  "serving": 6,
  "interest": 6,
  "prototype": 6,
  "numbers": 6,
  "concurrently": 6,
  "collation": 6,
  "matched": 6,
  "center": 6,
  "viewable": 6,
  "parameter": 6,
  "variables": 6,
  "short": 6,
  "anywhere": 6,
  "driven": 6,
  "linear": 6,
  "decay": 6,
  "navigate": 6,
  "reached": 6,
  "entered": 6,
  "pid": 6,
  "extra": 6,
  "implementation": 6,
  "arg": 6,
  "hourly": 6,
  "today": 6,
  "pivot": 6,
  "sorted": 6,
  "symbol": 6,
  "cid": 6,
  "reverse": 6,
  "transactions": 6,
  "positioned": 6,
  "literal": 6,
  "static": 6,
  "bottom": 6,
  "tbody": 6,
  "centered": 6,
  "headings": 6,
  "curr": 6,
  "mask": 6,
  "creds": 6,
  "breadcrumbs": 6,
  "incomplete": 6,
  "little": 6,
  "snippets": 6,
  "timing": 6,
  "iso": 6,
  "recursive": 6,
  "ae": 6,
  "mrr": 6,
  "software": 6,
  "euro": 6,
  "simplify": 6,
  "parser": 6,
  "splice": 6,
  "apollo": 6,
  "un": 6,
  "lte": 6,
  "slugify": 6,
  "simplification": 6,
  "logic": 6,
  "associations": 6,
  "diacritics": 6,
  "union": 6,
  "relationships": 6,
  "build": 6,
  "detected": 5,
  "sitelinks": 5,
  "searches": 5,
  "exp": 5,
  "decode": 5,
  "protocol": 5,
  "canonical": 5,
  "signature": 5,
  "speed": 5,
  "displayed": 5,
  "people": 5,
  "ip": 5,
  "carrier": 5,
  "interaction": 5,
  "universal": 5,
  "mongodb": 5,
  "picked": 5,
  "drop": 5,
  "executable": 5,
  "subtitle": 5,
  "dictionary": 5,
  "opt": 5,
  "move": 5,
  "begin": 5,
  "engagement": 5,
  "pre": 5,
  "install": 5,
  "sign": 5,
  "customers": 5,
  "highest": 5,
  "adjusted": 5,
  "covered": 5,
  "difference": 5,
  "super": 5,
  "undefined": 5,
  "registered": 5,
  "warning": 5,
  "destroy": 5,
  "invalidate": 5,
  "window": 5,
  "public": 5,
  "notifications": 5,
  "developer": 5,
  "updating": 5,
  "reload": 5,
  "completions": 5,
  "utm": 5,
  "prefer": 5,
  "rendered": 5,
  "footer": 5,
  "radius": 5,
  "bold": 5,
  "right": 5,
  "edited": 5,
  "selector": 5,
  "origin": 5,
  "totals": 5,
  "exception": 5,
  "year": 5,
  "ecpm": 5,
  "coverage": 5,
  "acquisition": 5,
  "batches": 5,
  "program": 5,
  "dir": 5,
  "vendor": 5,
  "tags": 5,
  "exist": 5,
  "verifications": 5,
  "deduplication": 5,
  "minimums": 5,
  "controller": 5,
  "authorization": 5,
  "media": 5,
  "logs": 5,
  "timeline": 5,
  "pipelines": 5,
  "permitted": 5,
  "mongod": 5,
  "attempts": 5,
  "possessives": 5,
  "querystring": 4,
  "f": 4,
  "placements": 4,
  "alias": 4,
  "real": 4,
  "performer": 4,
  "wikipedia": 4,
  "stripped": 4,
  "associated": 4,
  "memoized": 4,
  "usd": 4,
  "googlemaps": 4,
  "maps": 4,
  "point": 4,
  "endpoint": 4,
  "bit": 4,
  "flags": 4,
  "methods": 4,
  "thumbnail": 4,
  "rating": 4,
  "answer": 4,
  "quotes": 4,
  "localized": 4,
  "dangerously": 4,
  "configuration": 4,
  "approved": 4,
  "review": 4,
  "gender": 4,
  "biddable": 4,
  "gmail": 4,
  "cur": 4,
  "modified": 4,
  "that": 4,
  "verifiable": 4,
  "select": 4,
  "convert": 4,
  "reseller": 4,
  "evidences": 4,
  "enhanced": 4,
  "treatment": 4,
  "unsupported": 4,
  "aggressive": 4,
  "accepted": 4,
  "outbound": 4,
  "hotel": 4,
  "seconds": 4,
  "validate": 4,
  "ascending": 4,
  "initialization": 4,
  "synonyms": 4,
  "late": 4,
  "example": 4,
  "my": 4,
  "secondaries": 4,
  "suffix": 4,
  "finished": 4,
  "provide": 4,
  "deep": 4,
  "parsable": 4,
  "measure": 4,
  "iteration": 4,
  "append": 4,
  "wrong": 4,
  "bench": 4,
  "condition": 4,
  "pull": 4,
  "concern": 4,
  "spendings": 4,
  "actual": 4,
  "keep": 4,
  "bounced": 4,
  "doctype": 4,
  "preheader": 4,
  "tr": 4,
  "unit": 4,
  "units": 4,
  "strong": 4,
  "et": 4,
  "freeze": 4,
  "loaded": 4,
  "fixture": 4,
  "util": 4,
  "monitors": 4,
  "limiter": 4,
  "consider": 4,
  "matters": 4,
  "half": 4,
  "configure": 4,
  "continent": 4,
  "sample": 4,
  "interactions": 4,
  "exceptions": 4,
  "experiment": 4,
  "monetized": 4,
  "insertion": 4,
  "engine": 4,
  "refund": 4,
  "points": 4,
  "cli": 4,
  "initial": 4,
  "br": 4,
  "fresh": 4,
  "intents": 4,
  "assigning": 4,
  "traversed": 4,
  "utils": 4,
  "shows": 4,
  "placed": 4,
  "msg": 4,
  "verbose": 4,
  "trigger": 4,
  "fault": 4,
  "printer": 4,
  "icon": 4,
  "conditions": 4,
  "mime": 4,
  "won": 4,
  "currencies": 4,
  "participants": 4,
  "fail": 4,
  "labels": 4,
  "leads": 4,
  "notes": 4,
  "period": 4,
  "varchar": 4,
  "cursors": 4,
  "lines": 4,
  "occurence": 4,
  "booting": 4,
  "pos": 3,
  "less": 3,
  "performers": 3,
  "selection": 3,
  "flatten": 3,
  "googles": 3,
  "aggregated": 3,
  "affected": 3,
  "regexp": 3,
  "unauthorized": 3,
  "geocoding": 3,
  "integer": 3,
  "spam": 3,
  "linkingto": 3,
  "externallinks": 3,
  "externallinkstosubdomain": 3,
  "externallinkstorootdomain": 3,
  "blocks": 3,
  "timelastcrawled": 3,
  "encode": 3,
  "lhr": 3,
  "requested": 3,
  "failure": 3,
  "showing": 3,
  "also": 3,
  "eligible": 3,
  "approval": 3,
  "operating": 3,
  "youtube": 3,
  "payment": 3,
  "reasons": 3,
  "received": 3,
  "ct": 3,
  "already": 3,
  "widths": 3,
  "pad": 3,
  "cs": 3,
  "fr": 3,
  "enough": 3,
  "presence": 3,
  "constrained": 3,
  "adgroup": 3,
  "raise": 3,
  "bids": 3,
  "variable": 3,
  "spaces": 3,
  "sale": 3,
  "comparison": 3,
  "listing": 3,
  "bumper": 3,
  "skippable": 3,
  "true": 3,
  "commission": 3,
  "cpv": 3,
  "same": 3,
  "clients": 3,
  "fully": 3,
  "descending": 3,
  "shopware": 3,
  "starting": 3,
  "latest": 3,
  "rejects": 3,
  "reset": 3,
  "timezone": 3,
  "hashes": 3,
  "prepare": 3,
  "handled": 3,
  "yielded": 3,
  "processing": 3,
  "crawler": 3,
  "needs": 3,
  "feature": 3,
  "logged": 3,
  "eq": 3,
  "nin": 3,
  "throttled": 3,
  "unlock": 3,
  "performed": 3,
  "crucial": 3,
  "broader": 3,
  "expiry": 3,
  "exceeded": 3,
  "logo": 3,
  "shape": 3,
  "gray": 3,
  "hint": 3,
  "choice": 3,
  "recipients": 3,
  "hooks": 3,
  "reference": 3,
  "multiplier": 3,
  "usable": 3,
  "lookback": 3,
  "visitor": 3,
  "browser": 3,
  "exits": 3,
  "screenviews": 3,
  "appviews": 3,
  "screenview": 3,
  "sku": 3,
  "shipping": 3,
  "minute": 3,
  "spot": 3,
  "priorities": 3,
  "flattened": 3,
  "billing": 3,
  "contract": 3,
  "phase": 3,
  "free": 3,
  "online": 3,
  "div": 3,
  "met": 3,
  "todo": 3,
  "todos": 3,
  "responses": 3,
  "pathname": 3,
  "featured": 3,
  "images": 3,
  "variants": 3,
  "renames": 3,
  "forbidden": 3,
  "some": 3,
  "constructor": 3,
  "neighbors": 3,
  "ranked": 3,
  "exec": 3,
  "sizes": 3,
  "strip": 3,
  "inserted": 3,
  "plain": 3,
  "undone": 3,
  "took": 3,
  "www": 3,
  "datetime": 3,
  "formatter": 3,
  "must": 3,
  "inconsistent": 3,
  "audio": 3,
  "stop": 3,
  "cookie": 3,
  "lists": 3,
  "journeys": 3,
  "lost": 3,
  "quarterly": 3,
  "weekly": 3,
  "yearly": 3,
  "attachement": 3,
  "comments": 3,
  "movement": 3,
  "cancel": 3,
  "cadence": 3,
  "subscriptions": 3,
  "cookies": 3,
  "foreign": 3,
  "falsy": 3,
  "memory": 3,
  "workbook": 3,
  "colon": 3,
  "reflect": 3,
  "stored": 3,
  "light": 3,
  "stemmable": 3,
  "greater": 2,
  "better": 2,
  "worse": 2,
  "places": 2,
  "got": 2,
  "subtree": 2,
  "haystack": 2,
  "needles": 2,
  "needle": 2,
  "legal": 2,
  "characters": 2,
  "threshold": 2,
  "pow": 2,
  "sanitized": 2,
  "uniform": 2,
  "aud": 2,
  "bgn": 2,
  "brl": 2,
  "cad": 2,
  "chf": 2,
  "cny": 2,
  "czk": 2,
  "dkk": 2,
  "gbp": 2,
  "hkd": 2,
  "hrk": 2,
  "huf": 2,
  "idr": 2,
  "ils": 2,
  "inr": 2,
  "jpy": 2,
  "krw": 2,
  "mxn": 2,
  "myr": 2,
  "nok": 2,
  "nzd": 2,
  "php": 2,
  "pln": 2,
  "ron": 2,
  "rub": 2,
  "sek": 2,
  "sgd": 2,
  "thb": 2,
  "zar": 2,
  "binary": 2,
  "geocode": 2,
  "crypto": 2,
  "pagespeedonline": 2,
  "pagespeed": 2,
  "taken": 2,
  "hl": 2,
  "gl": 2,
  "information": 2,
  "reviews": 2,
  "gps": 2,
  "coordinates": 2,
  "safe": 2,
  "polish": 2,
  "sha": 2,
  "salt": 2,
  "rounds": 2,
  "helmet": 2,
  "incoming": 2,
  "tracing": 2,
  "backend": 2,
  "integrations": 2,
  "either": 2,
  "affinity": 2,
  "income": 2,
  "third": 2,
  "showcase": 2,
  "optimized": 2,
  "processes": 2,
  "updater": 2,
  "migrated": 2,
  "yet": 2,
  "attempt": 2,
  "instrument": 2,
  "truth": 2,
  "similarity": 2,
  "dont": 2,
  "care": 2,
  "targeted": 2,
  "help": 2,
  "partner": 2,
  "raises": 2,
  "medical": 2,
  "preventative": 2,
  "contraception": 2,
  "vaccine": 2,
  "standard": 2,
  "balanced": 2,
  "store": 2,
  "trough": 2,
  "backorder": 2,
  "preorder": 2,
  "subscriber": 2,
  "directive": 2,
  "cluster": 2,
  "os": 2,
  "master": 2,
  "instances": 2,
  "infinite": 2,
  "normal": 2,
  "bind": 2,
  "becomes": 2,
  "void": 2,
  "again": 2,
  "because": 2,
  "except": 2,
  "production": 2,
  "specified": 2,
  "expiration": 2,
  "elem": 2,
  "combined": 2,
  "ok": 2,
  "relevant": 2,
  "identities": 2,
  "deletable": 2,
  "percentage": 2,
  "finalizing": 2,
  "direct": 2,
  "juice": 2,
  "styles": 2,
  "lang": 2,
  "mg": 2,
  "username": 2,
  "contrast": 2,
  "canvas": 2,
  "hier": 2,
  "steht": 2,
  "die": 2,
  "zeilen": 2,
  "geht": 2,
  "ein": 2,
  "alles": 2,
  "sed": 2,
  "diam": 2,
  "button": 2,
  "arrow": 2,
  "prettify": 2,
  "successful": 2,
  "extendable": 2,
  "fixtures": 2,
  "unpaused": 2,
  "validation": 2,
  "neither": 2,
  "nor": 2,
  "paging": 2,
  "credential": 2,
  "mutate": 2,
  "whole": 2,
  "texts": 2,
  "given": 2,
  "included": 2,
  "sensitive": 2,
  "insensitive": 2,
  "explicitly": 2,
  "estimates": 2,
  "always": 2,
  "territory": 2,
  "translation": 2,
  "generating": 2,
  "referral": 2,
  "rpc": 2,
  "abandons": 2,
  "abandon": 2,
  "metro": 2,
  "city": 2,
  "refinements": 2,
  "redirection": 2,
  "interactive": 2,
  "tax": 2,
  "fatal": 2,
  "var": 2,
  "bracket": 2,
  "viewed": 2,
  "agency": 2,
  "coupon": 2,
  "refunds": 2,
  "beta": 2,
  "deduplicate": 2,
  "zip": 2,
  "kws": 2,
  "bound": 2,
  "skipped": 2,
  "ts": 2,
  "dirname": 2,
  "charging": 2,
  "pipe": 2,
  "drive": 2,
  "planned": 2,
  "flush": 2,
  "quota": 2,
  "paginated": 2,
  "systems": 2,
  "industries": 2,
  "authentications": 2,
  "probability": 2,
  "pass": 2,
  "emit": 2,
  "rss": 2,
  "published": 2,
  "grams": 2,
  "rename": 2,
  "marke": 2,
  "fake": 2,
  "reg": 2,
  "repeat": 2,
  "months": 2,
  "exclusions": 2,
  "predicted": 2,
  "serialized": 2,
  "shrinking": 2,
  "fitting": 2,
  "ancestor": 2,
  "most": 2,
  "parameterized": 2,
  "engines": 2,
  "longest": 2,
  "trimmed": 2,
  "iterables": 2,
  "repl": 2,
  "unbatched": 2,
  "sheets": 2,
  "execution": 2,
  "correct": 2,
  "locales": 2,
  "schemas": 2,
  "definitions": 2,
  "mixed": 2,
  "finite": 2,
  "go": 2,
  "popup": 2,
  "approximately": 2,
  "business": 2,
  "thirdparty": 2,
  "customizer": 2,
  "dsa": 2,
  "videos": 2,
  "present": 2,
  "calltracking": 2,
  "envelope": 2,
  "middleware": 2,
  "interests": 2,
  "vip": 2,
  "unsubscribe": 2,
  "assignedtouserid": 2,
  "star": 2,
  "deserialize": 2,
  "camel": 2,
  "voicemail": 2,
  "creator": 2,
  "subroles": 2,
  "dealid": 2,
  "opened": 2,
  "threads": 2,
  "folder": 2,
  "daterange": 2,
  "double": 2,
  "monetary": 2,
  "timerange": 2,
  "effective": 2,
  "duplex": 2,
  "export": 2,
  "populate": 2,
  "elapsed": 2,
  "unwrap": 2,
  "dot": 2,
  "foo": 2,
  "y": 2,
  "namespace": 2,
  "boot": 2,
  "derivational": 2,
  "augmentative": 2,
  "diminutive": 2,
  "comparative": 2,
  "stemword": 2,
  "argument": 1,
  "within": 1,
  "gu": 1,
  "aed": 1,
  "afn": 1,
  "amd": 1,
  "ang": 1,
  "aoa": 1,
  "ars": 1,
  "awg": 1,
  "azn": 1,
  "bam": 1,
  "bbd": 1,
  "bdt": 1,
  "bhd": 1,
  "bif": 1,
  "bmd": 1,
  "bnd": 1,
  "bob": 1,
  "bsd": 1,
  "btc": 1,
  "btn": 1,
  "bwp": 1,
  "byn": 1,
  "bzd": 1,
  "cdf": 1,
  "clf": 1,
  "clp": 1,
  "cnh": 1,
  "cop": 1,
  "crc": 1,
  "cuc": 1,
  "cup": 1,
  "cve": 1,
  "djf": 1,
  "dop": 1,
  "dzd": 1,
  "egp": 1,
  "ern": 1,
  "etb": 1,
  "fjd": 1,
  "fkp": 1,
  "gel": 1,
  "ggp": 1,
  "ghs": 1,
  "gip": 1,
  "gmd": 1,
  "gnf": 1,
  "gtq": 1,
  "gyd": 1,
  "hnl": 1,
  "htg": 1,
  "imp": 1,
  "iqd": 1,
  "irr": 1,
  "isk": 1,
  "jep": 1,
  "jmd": 1,
  "jod": 1,
  "kes": 1,
  "kgs": 1,
  "khr": 1,
  "kmf": 1,
  "kpw": 1,
  "kwd": 1,
  "kyd": 1,
  "kzt": 1,
  "lak": 1,
  "lbp": 1,
  "lkr": 1,
  "lrd": 1,
  "lsl": 1,
  "lyd": 1,
  "mad": 1,
  "mdl": 1,
  "mga": 1,
  "mkd": 1,
  "mmk": 1,
  "mnt": 1,
  "mop": 1,
  "mro": 1,
  "mru": 1,
  "mur": 1,
  "mvr": 1,
  "mwk": 1,
  "mzn": 1,
  "nad": 1,
  "ngn": 1,
  "nio": 1,
  "npr": 1,
  "omr": 1,
  "pab": 1,
  "pen": 1,
  "pgk": 1,
  "pkr": 1,
  "pyg": 1,
  "qar": 1,
  "rsd": 1,
  "rwf": 1,
  "sar": 1,
  "sbd": 1,
  "scr": 1,
  "sdg": 1,
  "shp": 1,
  "sll": 1,
  "sos": 1,
  "srd": 1,
  "ssp": 1,
  "std": 1,
  "stn": 1,
  "svc": 1,
  "syp": 1,
  "szl": 1,
  "tjs": 1,
  "tmt": 1,
  "tnd": 1,
  "ttd": 1,
  "twd": 1,
  "tzs": 1,
  "uah": 1,
  "ugx": 1,
  "uyu": 1,
  "uzs": 1,
  "ves": 1,
  "vnd": 1,
  "vuv": 1,
  "wst": 1,
  "xaf": 1,
  "xag": 1,
  "xau": 1,
  "xcd": 1,
  "xdr": 1,
  "xof": 1,
  "xpd": 1,
  "xpf": 1,
  "xpt": 1,
  "yer": 1,
  "zmw": 1,
  "zwl": 1,
  "plus": 1,
  "unix": 1,
  "hmac": 1,
  "cols": 1,
  "sockets": 1,
  "searchanalytics": 1,
  "bewertung": 1,
  "rezensionen": 1,
  "processed": 1,
  "box": 1,
  "altitude": 1,
  "lsig": 1,
  "founded": 1,
  "headquarters": 1,
  "ceo": 1,
  "founders": 1,
  "subsidiaries": 1,
  "stick": 1,
  "question": 1,
  "uule": 1,
  "lr": 1,
  "nfpr": 1,
  "tbm": 1,
  "tbs": 1,
  "ijn": 1,
  "spell": 1,
  "receive": 1,
  "components": 1,
  "dsn": 1,
  "traces": 1,
  "sampler": 1,
  "sampling": 1,
  "release": 1,
  "req": 1,
  "security": 1,
  "handlers": 1,
  "listen": 1,
  "rarely": 1,
  "served": 1,
  "disapproved": 1,
  "partition": 1,
  "proximity": 1,
  "platform": 1,
  "disapproval": 1,
  "party": 1,
  "snapshot": 1,
  "own": 1,
  "moden": 1,
  "zz": 1,
  "von": 1,
  "ignoring": 1,
  "subsequent": 1,
  "sparse": 1,
  "defs": 1,
  "express": 1,
  "measuring": 1,
  "unshift": 1,
  "german": 1,
  "english": 1,
  "french": 1,
  "phasing": 1,
  "optimizer": 1,
  "eligibility": 1,
  "rejection": 1,
  "area": 1,
  "assets": 1,
  "prohibited": 1,
  "limited": 1,
  "websites": 1,
  "decisions": 1,
  "modifier": 1,
  "manufacturer": 1,
  "suspended": 1,
  "economical": 1,
  "converted": 1,
  "imported": 1,
  "pone": 1,
  "alcohol": 1,
  "animals": 1,
  "beauty": 1,
  "cosmetics": 1,
  "electronics": 1,
  "fashion": 1,
  "apparel": 1,
  "food": 1,
  "beverage": 1,
  "health": 1,
  "living": 1,
  "sports": 1,
  "utilities": 1,
  "disliked": 1,
  "neutral": 1,
  "overwrite": 1,
  "transform": 1,
  "magento": 1,
  "woo": 1,
  "cleared": 1,
  "cpus": 1,
  "spawning": 1,
  "died": 1,
  "inc": 1,
  "finalization": 1,
  "what": 1,
  "arguments": 1,
  "determining": 1,
  "whether": 1,
  "unexpected": 1,
  "similar": 1,
  "buckets": 1,
  "calling": 1,
  "scheduling": 1,
  "hourglass": 1,
  "flowing": 1,
  "sand": 1,
  "white": 1,
  "octagonal": 1,
  "occurred": 1,
  "which": 1,
  "indicates": 1,
  "something": 1,
  "went": 1,
  "successfully": 1,
  "reading": 1,
  "support": 1,
  "environments": 1,
  "projectstatistics": 1,
  "productcategories": 1,
  "productfeeds": 1,
  "productfeeditems": 1,
  "cachedrequests": 1,
  "rawanalysisrows": 1,
  "pageanalysisrows": 1,
  "pageassociationsuggestions": 1,
  "analysisprogress": 1,
  "adwordscampaigns": 1,
  "adwordsadgroups": 1,
  "adwordsadgroupads": 1,
  "adwordssearchquerymappings": 1,
  "adwordsboomeranktrackedkeywords": 1,
  "googleadsboomerankbiddingstrategies": 1,
  "googleadshistoryevents": 1,
  "keywordgenerationprocesses": 1,
  "urltechscores": 1,
  "urlcontentscores": 1,
  "urlmozscores": 1,
  "domainlocations": 1,
  "googleadskeywordstats": 1,
  "entitymetrics": 1,
  "projectmetrics": 1,
  "googleadsperformancereports": 1,
  "searchqueryalternatives": 1,
  "adwordsboomerankadgroups": 1,
  "adwordsboomerankadgroupads": 1,
  "seaefficiencyactions": 1,
  "analysisjobs": 1,
  "globalkeywordblacklists": 1,
  "globalkeywordblacklistslices": 1,
  "googleadsbudgets": 1,
  "badperformingkeywords": 1,
  "cachedprojectmetrics": 1,
  "apicalls": 1,
  "googleadsapicalls": 1,
  "pausedads": 1,
  "organickeywordperformance": 1,
  "ecommercerelevancejob": 1,
  "googleadscampaigns": 1,
  "googleadsadgroups": 1,
  "googleadsadtemplates": 1,
  "pausedgoogleadskeywords": 1,
  "googleadsbiddingstrategies": 1,
  "googleadssharedbudgets": 1,
  "googleadsperformancereportcache": 1,
  "trackedstories": 1,
  "mailchimpactivity": 1,
  "globalconfig": 1,
  "early": 1,
  "versions": 1,
  "mutations": 1,
  "accuracy": 1,
  "defaulted": 1,
  "ignore": 1,
  "relations": 1,
  "identifier": 1,
  "unified": 1,
  "polling": 1,
  "bgcolor": 1,
  "seal": 1,
  "sendable": 1,
  "overriding": 1,
  "valign": 1,
  "decoration": 1,
  "anchor": 1,
  "typ": 1,
  "eine": 1,
  "berschrift": 1,
  "maximal": 1,
  "ber": 1,
  "zwei": 1,
  "kurzer": 1,
  "dreizeiler": 1,
  "der": 1,
  "wichtigsten": 1,
  "dinge": 1,
  "zusammenfasst": 1,
  "ohne": 1,
  "dass": 1,
  "leser": 1,
  "lesen": 1,
  "muss": 1,
  "darum": 1,
  "wichtige": 1,
  "einem": 1,
  "zusammenzufassen": 1,
  "abs": 1,
  "tze": 1,
  "solten": 1,
  "nur": 1,
  "enthalten": 1,
  "lorem": 1,
  "ipsum": 1,
  "dolor": 1,
  "sit": 1,
  "amet": 1,
  "consetetur": 1,
  "sadipscing": 1,
  "elitr": 1,
  "nonumy": 1,
  "eirmod": 1,
  "tempor": 1,
  "invidunt": 1,
  "ut": 1,
  "labore": 1,
  "dolore": 1,
  "magna": 1,
  "aliquyam": 1,
  "erat": 1,
  "voluptua": 1,
  "vero": 1,
  "eos": 1,
  "accusam": 1,
  "justo": 1,
  "duo": 1,
  "dolores": 1,
  "ea": 1,
  "rebum": 1,
  "subvalue": 1,
  "recipient": 1,
  "translated": 1,
  "descriptive": 1,
  "ur": 1,
  "ls": 1,
  "cc": 1,
  "but": 1,
  "protobuf": 1,
  "breadcrum": 1,
  "truncate": 1,
  "fit": 1,
  "possible": 1,
  "hex": 1,
  "outstream": 1,
  "trueview": 1,
  "onclick": 1,
  "mutable": 1,
  "analyticsadmin": 1,
  "visitors": 1,
  "bounces": 1,
  "slot": 1,
  "roi": 1,
  "completion": 1,
  "branding": 1,
  "flash": 1,
  "java": 1,
  "colors": 1,
  "resolution": 1,
  "entrances": 1,
  "entrance": 1,
  "refinement": 1,
  "uniques": 1,
  "latency": 1,
  "installer": 1,
  "affiliation": 1,
  "purchases": 1,
  "market": 1,
  "traffic": 1,
  "hierarchy": 1,
  "buy": 1,
  "calc": 1,
  "retention": 1,
  "hits": 1,
  "adds": 1,
  "checkouts": 1,
  "removes": 1,
  "checked": 1,
  "refunded": 1,
  "analyticsreporting": 1,
  "ranges": 1,
  "expression": 1,
  "tagmanager": 1,
  "csm": 1,
  "didn": 1,
  "adding": 1,
  "promises": 1,
  "readdir": 1,
  "doesn": 1,
  "where": 1,
  "persisting": 1,
  "attempting": 1,
  "fetching": 1,
  "good": 1,
  "broken": 1,
  "trial": 1,
  "until": 1,
  "geq": 1,
  "awaited": 1,
  "wizard": 1,
  "projekt": 1,
  "productfeed": 1,
  "ratelimit": 1,
  "merging": 1,
  "rewriting": 1,
  "secure": 1,
  "alt": 1,
  "requires": 1,
  "taxable": 1,
  "titel": 1,
  "beschreibung": 1,
  "preis": 1,
  "basename": 1,
  "reducer": 1,
  "sqrt": 1,
  "divide": 1,
  "multiply": 1,
  "commit": 1,
  "closest": 1,
  "equiv": 1,
  "defer": 1,
  "cross": 1,
  "noscript": 1,
  "iframe": 1,
  "categorybrand": 1,
  "hersteller": 1,
  "kategor": 1,
  "categor": 1,
  "sortiment": 1,
  "excludes": 1,
  "cond": 1,
  "bodyparser": 1,
  "passport": 1,
  "serve": 1,
  "decompose": 1,
  "nestjs": 1,
  "customizers": 1,
  "modify": 1,
  "sharing": 1,
  "flexible": 1,
  "false": 1,
  "subclass": 1,
  "mobileads": 1,
  "beacon": 1,
  "domestic": 1,
  "emergency": 1,
  "incorrect": 1,
  "ineligible": 1,
  "upgrade": 1,
  "certified": 1,
  "wide": 1,
  "advertisement": 1,
  "distinct": 1,
  "temp": 1,
  "malformed": 1,
  "equivalent": 1,
  "expandable": 1,
  "retrieval": 1,
  "incompatible": 1,
  "preference": 1,
  "specific": 1,
  "disallowed": 1,
  "premium": 1,
  "consent": 1,
  "recording": 1,
  "faultcode": 1,
  "faultstring": 1,
  "mimetype": 1,
  "encoding": 1,
  "tld": 1,
  "fname": 1,
  "lname": 1,
  "web": 1,
  "consents": 1,
  "messaging": 1,
  "orders": 1,
  "authentication": 1,
  "fragment": 1,
  "pipes": 1,
  "ssv": 1,
  "tsv": 1,
  "jsonified": 1,
  "assignee": 1,
  "parties": 1,
  "general": 1,
  "currencyid": 1,
  "stageid": 1,
  "stageidcurrencyid": 1,
  "formatted": 1,
  "between": 1,
  "duplicated": 1,
  "mailbox": 1,
  "churn": 1,
  "contraction": 1,
  "expansion": 1,
  "pictures": 1,
  "recent": 1,
  "requred": 1,
  "plugins": 1,
  "acl": 1,
  "ca": 1,
  "cert": 1,
  "del": 1,
  "tls": 1,
  "certs": 1,
  "mkactivity": 1,
  "mkcalendar": 1,
  "mkcol": 1,
  "notify": 1,
  "once": 1,
  "patch": 1,
  "pfx": 1,
  "pri": 1,
  "propfind": 1,
  "proppatch": 1,
  "purge": 1,
  "rebind": 1,
  "redirects": 1,
  "unbind": 1,
  "unlink": 1,
  "jar": 1,
  "paper": 1,
  "bits": 1,
  "infinity": 1,
  "shift": 1,
  "parents": 1,
  "punctuation": 1,
  "checkpoint": 1,
  "cp": 1,
  "truthy": 1,
  "foobar": 1,
  "operators": 1,
  "nested": 1,
  "ordered": 1,
  "intersection": 1,
  "blankrows": 1,
  "processors": 1,
  "queueing": 1,
  "bootstrapper": 1,
  "parallel": 1
}